pandas3js/__init__.py
pandas3js/utils.py
pandas3js/atom/__init__.py
pandas3js/atom/utils.py
pandas3js/atom/data/__init__.py
pandas3js/atom/data/atomdata_map.csv
pandas3js/models/__init__.py
pandas3js/models/idcollection.py
pandas3js/models/idobject.py
pandas3js/views/__init__.py
pandas3js/views/jsgui.py
pandas3js/views/jsmapping.py
pandas3js/views/jsmesh.py
pandas3js/views/jsrenderer.py
pandas3js/views/jsscene.py
pandas3js-0.2.0.dist-info/DESCRIPTION.rst
pandas3js-0.2.0.dist-info/METADATA
pandas3js-0.2.0.dist-info/RECORD
pandas3js-0.2.0.dist-info/WHEEL
pandas3js-0.2.0.dist-info/metadata.json
pandas3js-0.2.0.dist-info/top_level.txt
pandas3js-0.2.0.dist-info/zip-safe
