Metadata-Version: 2.0
Name: pandas3js
Version: 0.2.0
Summary: a pandas dataframe interface for traitlets and pythreejs
Home-page: https://github.com/chrisjsewell/pandas3js
Author: Chris Sewell
Author-email: chrisj_sewell@hotmail.com
License: MIT
Keywords: pythreejs,traitlets,graphics,3D,pandas,ipython,jupyter,three.js,webgl
Platform: UNKNOWN
Classifier: Development Status :: 3 - Alpha
Classifier: Environment :: Console
Classifier: Environment :: Web Environment
Classifier: Intended Audience :: End Users/Desktop
Classifier: Intended Audience :: Science/Research
Classifier: License :: OSI Approved :: MIT License
Classifier: Operating System :: OS Independent
Classifier: Programming Language :: Python
Classifier: Programming Language :: Python :: 2
Classifier: Programming Language :: Python :: 2.7
Classifier: Programming Language :: Python :: 3
Classifier: Programming Language :: Python :: 3.4
Classifier: Programming Language :: Python :: 3.5
Classifier: Topic :: Scientific/Engineering :: Chemistry
Classifier: Topic :: Scientific/Engineering :: Physics
Classifier: Topic :: Software Development :: Libraries :: Python Modules
Requires-Dist: ipython
Requires-Dist: ipywidgets
Requires-Dist: matplotlib (>=2)
Requires-Dist: numpy
Requires-Dist: pandas
Requires-Dist: pythreejs
Requires-Dist: traitlets
